taxi_data/__init__.py
taxi_data/automate_bwc_web_site.py
taxi_data/automate_gps_tracker_web_site.py
taxi_data/classes.py
taxi_data/constants.py
taxi_data/coords_times_jobs.py
taxi_data/get_job_list.py
taxi_data/get_kml_file.py
taxi_data/make_gps_data_from_playback.py
taxi_data/make_gps_jobs.py
taxi_data/parse_kml.py
taxi_data/poi_map.py
taxi_data/requirements.txt
taxi_data/setup.py
taxi_data/visualize_jobs_on_map.py
taxi_data-0.0.13.dist-info/METADATA
taxi_data-0.0.13.dist-info/WHEEL
taxi_data-0.0.13.dist-info/licenses/LICENSE
taxi_data-0.0.13.dist-info/RECORD
