Metadata-Version: 2.3
Name: taxi_data
Version: 0.0.13
Summary: Export data from web portals and build GPS data set.
Project-URL: Homepage, https://github.com/WayneBennett666/taxi-data
Project-URL: Issues, https://github.com/WayneBennett666/taxi-data/issues
Author-email: Wayne Bennett <wayne.bennett@live.com>
License-File: LICENSE
Classifier: License :: OSI Approved :: MIT License
Classifier: Operating System :: OS Independent
Classifier: Programming Language :: Python :: 3
Requires-Python: >=3.10
